docs/Makefile
docs/__init__.py
docs/make.bat
docs/source/_pages/contact.rst
docs/source/_static/css/custom.css
docs/source/_static/css/style.css
docs/source/conf.py
docs/source/index.rst
qtpygraph/__init__.py
qtpygraph/__main__.py
qtpygraph/py.typed
stubs/PySide6-stubs/Qt3DAnimation/_Qt3DAnimation.pyi
stubs/PySide6-stubs/Qt3DAnimation/__init__.pyi
stubs/PySide6-stubs/Qt3DAnimation/_functions.pyi
stubs/PySide6-stubs/Qt3DCore/_Qt3DCore.pyi
stubs/PySide6-stubs/Qt3DCore/__init__.pyi
stubs/PySide6-stubs/Qt3DCore/_functions.pyi
stubs/PySide6-stubs/Qt3DExtras/_Qt3DExtras.pyi
stubs/PySide6-stubs/Qt3DExtras/__init__.pyi
stubs/PySide6-stubs/Qt3DExtras/_functions.pyi
stubs/PySide6-stubs/Qt3DInput/_QIntList.pyi
stubs/PySide6-stubs/Qt3DInput/_Qt3DInput.pyi
stubs/PySide6-stubs/Qt3DInput/__init__.pyi
stubs/PySide6-stubs/Qt3DInput/_functions.pyi
stubs/PySide6-stubs/Qt3DLogic/_Qt3DLogic.pyi
stubs/PySide6-stubs/Qt3DLogic/__init__.pyi
stubs/PySide6-stubs/Qt3DLogic/_functions.pyi
stubs/PySide6-stubs/Qt3DRender/_QIntList.pyi
stubs/PySide6-stubs/Qt3DRender/_Qt3DRender.pyi
stubs/PySide6-stubs/Qt3DRender/__init__.pyi
stubs/PySide6-stubs/Qt3DRender/_functions.pyi
stubs/PySide6-stubs/QtAxContainer/_QAxBase.pyi
stubs/PySide6-stubs/QtAxContainer/_QAxBaseObject.pyi
stubs/PySide6-stubs/QtAxContainer/_QAxBaseWidget.pyi
stubs/PySide6-stubs/QtAxContainer/_QAxObject.pyi
stubs/PySide6-stubs/QtAxContainer/_QAxObjectInterface.pyi
stubs/PySide6-stubs/QtAxContainer/_QAxScript.pyi
stubs/PySide6-stubs/QtAxContainer/_QAxScriptEngine.pyi
stubs/PySide6-stubs/QtAxContainer/_QAxScriptManager.pyi
stubs/PySide6-stubs/QtAxContainer/_QAxSelect.pyi
stubs/PySide6-stubs/QtAxContainer/_QAxWidget.pyi
stubs/PySide6-stubs/QtAxContainer/__init__.pyi
stubs/PySide6-stubs/QtAxContainer/_functions.pyi
stubs/PySide6-stubs/QtBluetooth/_QBluetooth.pyi
stubs/PySide6-stubs/QtBluetooth/_QBluetoothAddress.pyi
stubs/PySide6-stubs/QtBluetooth/_QBluetoothDeviceDiscoveryAgent.pyi
stubs/PySide6-stubs/QtBluetooth/_QBluetoothDeviceInfo.pyi
qtpygraph-0.3.0.dist-info/LICENSE
qtpygraph-0.3.0.dist-info/WHEEL
qtpygraph-0.3.0.dist-info/METADATA
qtpygraph-0.3.0.dist-info/RECORD
