Metadata-Version: 2.1
Name: qtpygraph
Version: 0.3.0
Summary: A pythonic interface to the Qt Graphics View Framework using qtpy
Home-page: https://github.com/adam-grant-hendry/qtpygraph
License: Apache-2.0
Author: Hendry, Adam
Author-email: adam.grant.hendry@gmail.com
Requires-Python: >=3.8,<3.11
Classifier: License :: OSI Approved :: Apache Software License
Classifier: Operating System :: MacOS :: MacOS X
Classifier: Operating System :: Microsoft :: Windows :: Windows 10
Classifier: Operating System :: POSIX :: Linux
Classifier: Programming Language :: Python :: 3
Classifier: Programming Language :: Python :: 3.8
Classifier: Programming Language :: Python :: 3.9
Classifier: Programming Language :: Python :: 3.10
Classifier: Programming Language :: Python :: 3
Classifier: Programming Language :: Python :: 3.10
Classifier: Programming Language :: Python :: 3.8
Classifier: Programming Language :: Python :: 3.9
Requires-Dist: PyYAML (>=6.0)
Requires-Dist: QtPy (>=2.1.0)
Requires-Dist: Sphinx (>=4.5.0)
Requires-Dist: add-trailing-comma (>=2.2.3)
Requires-Dist: appdirs (>=1.4.4)
Requires-Dist: beautifulsoup4 (>=4.11.1)
Requires-Dist: black (>=22.3.0)
Requires-Dist: blackdoc (>=0.3.4)
Requires-Dist: blacken-docs (>=1.12.1)
Requires-Dist: check-jsonschema (>=0.14.3)
Requires-Dist: codecov (>=2.1.12)
Requires-Dist: codespell (>=2.1.0)
Requires-Dist: coverage[toml] (>=6.4)
Requires-Dist: doc8 (>=0.11.2)
Requires-Dist: docformatter (>=1.4)
Requires-Dist: flake8 (>=4.0.1)
Requires-Dist: flake8-bugbear (>=22.9.11)
Requires-Dist: flake8-quotes (>=3.3.1)
Requires-Dist: glfw (>=2.5.3)
Requires-Dist: graphviz (>=0.20)
Requires-Dist: h5py (>=3.6.0)
Requires-Dist: html5lib (>=1.1)
Requires-Dist: hypothesis (>=6.46.2)
Requires-Dist: instaviz (>=0.6.0)
Requires-Dist: ipdb (>=0.13.9)
Requires-Dist: ipython (>=8.3.0)
Requires-Dist: isort (>=5.10.1)
Requires-Dist: lxml (>=4.8.0)
Requires-Dist: matplotlib (>=3.5.2)
Requires-Dist: memory-profiler (>=0.60.0)
Requires-Dist: merry (>=0.3.0)
Requires-Dist: mypy (>=0.961)
Requires-Dist: mypy-extensions (>=0.4.3)
Requires-Dist: myst-parser (>=0.17.2)
Requires-Dist: ninja (>=1.10.2)
Requires-Dist: numpy (>=1.22.3)
Requires-Dist: numpydoc (>=1.4.0)
Requires-Dist: objgraph (>=3.5.0)
Requires-Dist: opencv-python (>=4.5.5.64)
Requires-Dist: pep8-naming (>=0.12.1)
Requires-Dist: pre-commit (>=2.18.1)
Requires-Dist: pycln (>=1.3.5)
Requires-Dist: pydantic (>=1.9.1)
Requires-Dist: pydocstringformatter (>=0.7.0)
Requires-Dist: pydocstyle[toml] (>=6.1.1)
Requires-Dist: pyinstaller (>=5.1)
Requires-Dist: pylint (>=2.13.8)
Requires-Dist: pyright (>=1.1.253)
Requires-Dist: pytest (>=7.1.2)
Requires-Dist: pytest-cov (>=3.0.0)
Requires-Dist: pytest-doctestplus (>=0.12.0)
Requires-Dist: pytest-env (>=0.6.2)
Requires-Dist: pytest-memprof (>=0.2.0)
Requires-Dist: pytest-mock (>=3.7.0)
Requires-Dist: pytest-qt (>=4.0.2)
Requires-Dist: pytest-randomly (>=3.11.0)
Requires-Dist: pytest-xdist (>=2.5.0)
Requires-Dist: pyupgrade (>=2.34.0)
Requires-Dist: requests (>=2.27.1)
Requires-Dist: rstcheck[sphinx,toml] (>=5.0.0)
Requires-Dist: seedir (>=0.3.0)
Requires-Dist: setuptools (>=65.3.0,<66.0.0)
Requires-Dist: setuptools-scm (>=7.0.5,<8.0.0)
Requires-Dist: sphinx-book-theme (>=0.3.3,<0.4.0)
Requires-Dist: sphinxcontrib-email (>=0.3.5)
Requires-Dist: sphinxcontrib-mermaid (>=0.7.1,<0.8.0)
Requires-Dist: sphinxcontrib-napoleon (>=0.7)
Requires-Dist: toml (>=0.10.2)
Requires-Dist: tomli (>=2.0.1)
Requires-Dist: tox (>=3.25.0)
Requires-Dist: tqdm (>=4.64.0)
Requires-Dist: tqdm-stubs (>=0.2.0)
Requires-Dist: types-beautifulsoup4 (>=4.11.1)
Requires-Dist: types-setuptools (>=57.4.17)
Requires-Dist: types-toml (>=0.10.7)
Requires-Dist: typing-extensions (>=4.2.0)
Requires-Dist: vulture (>=2.3)
Requires-Dist: wheel (>=0.37.1)
Project-URL: Repository, https://github.com/adam-grant-hendry/qtpygraph
